iLibrary/__init__.py
iLibrary/src/Library.py
iLibrary/src/User.py
iLibrary/src/__init__.py
iLibrary/src/getInfoForLibrary.py
iLibrary/src/getUserInfoForUser.py
iLibrary/src/saveLibrary.py
iLibrary/tests/__init__.py
iLibrary/tests/test_getSavf.py
ilibrary-0.0.13.dist-info/licenses/LICENSE.txt
ilibrary-0.0.13.dist-info/METADATA
ilibrary-0.0.13.dist-info/WHEEL
ilibrary-0.0.13.dist-info/top_level.txt
ilibrary-0.0.13.dist-info/RECORD
