Metadata-Version: 2.4
Name: iLibrary
Version: 0.0.13
Summary: iLibrary - Tools for IBM i library
Home-page: https://legner.beer
Author: jgh1
Author-email: iLibrary@legner.beer
Project-URL: Bug Tracker, https://legner.beer/bugs
Project-URL: Git Hub, https://github.com/jgh1/iLibrary
Classifier: Programming Language :: Python :: 3
Classifier: License :: OSI Approved :: MIT License
Classifier: Development Status :: 4 - Beta
Classifier: Operating System :: OS Independent
Requires-Python: >=3.6
License-File: LICENSE.txt
Dynamic: author
Dynamic: author-email
Dynamic: classifier
Dynamic: description
Dynamic: description-content-type
Dynamic: home-page
Dynamic: license-file
Dynamic: project-url
Dynamic: requires-python
Dynamic: summary
